CHANGELOG.txt
LICENSE.txt
MANIFEST.in
README.txt
app.py
setup.py
bazregarimodule.egg-info/PKG-INFO
bazregarimodule.egg-info/SOURCES.txt
bazregarimodule.egg-info/dependency_links.txt
bazregarimodule.egg-info/top_level.txt