Metadata-Version: 1.1
Name: bazregarimodule
Version: 0.0.1
Summary: A very basic calculator
Home-page: UNKNOWN
Author: Ali asgar Bazregari
Author-email: bazregaridev01@gmail.com
License: MIT
Keywords: calculator
Platform: UNKNOWN
Classifier: Development Status :: 5 - Production/Stable
Classifier: Intended Audience :: Education
Classifier: Operating System :: Microsoft :: Windows :: Windows 10
Classifier: License :: OSI Approved :: MIT License
Classifier: Programming Language :: Python :: 3
